attractors/__init__.py
attractors/py.typed
attractors/type_defs.py
attractors/solvers/__init__.py
attractors/solvers/core.py
attractors/solvers/euler.py
attractors/solvers/registry.py
attractors/solvers/rk2.py
attractors/solvers/rk3.py
attractors/solvers/rk4.py
attractors/solvers/rk5.py
attractors/systems/__init__.py
attractors/systems/bouali.py
attractors/systems/burke_shaw.py
attractors/systems/chen.py
attractors/systems/chen_lee.py
attractors/systems/chen_lu.py
attractors/systems/dadras.py
attractors/systems/dequan_li.py
attractors/systems/finance.py
attractors/systems/hadley.py
attractors/systems/halvorsen.py
attractors/systems/langford.py
attractors/systems/lorenz.py
attractors/systems/lotka_volterra.py
attractors/systems/moore_spiegel.py
attractors/systems/newton_leipnik.py
attractors/systems/nose_hoover.py
attractors/systems/rabinovich_fabrikant.py
attractors/systems/registry.py
attractors/systems/rikitake.py
attractors/systems/rossler.py
attractors/systems/rucklidge.py
attractors/systems/sakarya.py
attractors/systems/shimizu_morioka.py
attractors/systems/thomas.py
attractors/systems/three_cell_cnn.py
attractors/systems/wang_sun.py
attractors/systems/yu_wang.py
attractors/themes/__init__.py
attractors/themes/manager.py
attractors/themes/theme.py
attractors/utils/__init__.py
attractors/utils/logger.py
attractors/visualizers/__init__.py
attractors/visualizers/animate.py
attractors/visualizers/base.py
attractors/visualizers/static.py
attractors/visualizers/utils/color_mapper.py
attractors/visualizers/utils/downsampler.py
attractors-2.0.0.dist-info/LICENSE
attractors-2.0.0.dist-info/METADATA
attractors-2.0.0.dist-info/WHEEL
attractors-2.0.0.dist-info/top_level.txt
attractors-2.0.0.dist-info/RECORD
