Metadata-Version: 2.2
Name: attractors
Version: 2.0.0
Summary: A package for simulation and visualization of strange attractors
Author-email: vdesmond <vignesh.desmond@gmail.com>
Project-URL: Homepage, https://github.com/vdesmond/attractors
Project-URL: Bug Tracker, https://github.com/vdesmond/attractors/issues
Project-URL: Discussions, https://github.com/vdesmond/attractors/discussions
Project-URL: Changelog, https://github.com/vdesmond/attractors/releases
Classifier: Development Status :: 5 - Production/Stable
Classifier: Intended Audience :: Science/Research
Classifier: Intended Audience :: Developers
Classifier: License :: OSI Approved :: MIT License
Classifier: Operating System :: OS Independent
Classifier: Programming Language :: Python
Classifier: Programming Language :: Python :: 3
Classifier: Programming Language :: Python :: 3 :: Only
Classifier: Programming Language :: Python :: 3.11
Classifier: Programming Language :: Python :: 3.12
Classifier: Programming Language :: Python :: 3.13
Classifier: Topic :: Scientific/Engineering
Classifier: Typing :: Typed
Requires-Python: >=3.11
License-File: LICENSE
Requires-Dist: matplotlib>=3.10.0
Requires-Dist: numba>=0.60.0
Requires-Dist: numpy>=2.0.2
Requires-Dist: setuptools>=75.7.0
